dsolve/__init__.py
dsolve/atoms.py
dsolve/expressions.py
dsolve/linearization.py
dsolve/solvers.py
dsolve/statespace.py
dsolve/utils.py
dsolve/sequence_space/__init__.py
dsolve/sequence_space/sequence_space.py
dsolve-0.0.17.dist-info/METADATA
dsolve-0.0.17.dist-info/WHEEL
dsolve-0.0.17.dist-info/top_level.txt
dsolve-0.0.17.dist-info/RECORD
