Metadata-Version: 2.1
Name: dsolve
Version: 0.0.17
Summary: Solver of dynamic equations with forward looking variables
Home-page: https://github.com/marcdelabarrera/dsolve
Author: Marc de la Barrera i Bardalet
Author-email: mbarrera@mit.edu
Classifier: Programming Language :: Python :: 3.10
Requires-Dist: scipy (>=1.9.0)
Requires-Dist: sympy (>=1.11)
Requires-Dist: numpy (>=1.20.0)
Requires-Dist: IPython (>=7.12.0)
Requires-Dist: jax (>=0.4)
Provides-Extra: dev
Requires-Dist: pytest (>=7.1.2) ; extra == 'dev'
